acs_cli-0.0.9.dist-info/DESCRIPTION.rst
acs_cli-0.0.9.dist-info/METADATA
acs_cli-0.0.9.dist-info/RECORD
acs_cli-0.0.9.dist-info/WHEEL
acs_cli-0.0.9.dist-info/entry_points.txt
acs_cli-0.0.9.dist-info/metadata.json
acs_cli-0.0.9.dist-info/top_level.txt
acscli/__init__.py
acscli/acs.py
acscli/api_defs.py
acscli/auth.py
acscli/client.py
acscli/common.py
acscli/conventions.py
acscli/example.py
acscli/formats.py
acscli/people.py
acscli/sites.py
acscli/test_acs.py
acscli/test_client.py
acscli/test_conventions.py
acscli/test_formats.py
