Metadata-Version: 2.0
Name: acs-cli
Version: 0.0.9
Summary: A command line interface to the Alfresco Content Services REST API
Home-page: https://git.alfresco.com/mward/acs-cli
Author: Matt Ward
Author-email: matt.ward@alfresco.com
License: UNKNOWN
Keywords: alfresco acs rest cli
Platform: UNKNOWN
Classifier: Development Status :: 3 - Alpha
Classifier: Intended Audience :: Developers
Classifier: Topic :: Utilities
Classifier: Programming Language :: Python :: 3
Requires-Dist: argcomplete
Requires-Dist: jmespath
Requires-Dist: requests
Provides-Extra: dev
Requires-Dist: check-manifest; extra == 'dev'
Provides-Extra: test
Requires-Dist: coverage; extra == 'test'
